wenet/__init__.py
wenet/bin/alignment.py
wenet/bin/average_model.py
wenet/bin/average_model_fixed_list.py
wenet/bin/ctc_align.py
wenet/bin/export_ipex.py
wenet/bin/export_jit.py
wenet/bin/export_onnx.py
wenet/bin/export_onnx_bpu.py
wenet/bin/export_onnx_cpu.py
wenet/bin/export_onnx_gpu.py
wenet/bin/get_loss.py
wenet/bin/recognize.py
wenet/bin/recognize_onnx_gpu.py
wenet/bin/recognize_wav.py
wenet/bin/train.py
wenet/bin/train.teacher-student.py
wenet/bin/train.torchrun.py
wenet/branchformer/__init__.py
wenet/branchformer/cgmlp.py
wenet/branchformer/encoder.py
wenet/branchformer/encoder_layer.py
wenet/cli/__init__.py
wenet/cli/hub.py
wenet/cli/model.py
wenet/cli/paraformer_model.py
wenet/cli/reverb.py
wenet/cli/transcribe.py
wenet/cli/utils.py
wenet/ctl_model/asr_model_ctl.py
wenet/ctl_model/encoder.py
wenet/dataset/__init__.py
wenet/dataset/audio_utils.py
wenet/dataset/datapipes.py
wenet/dataset/dataset.py
wenet/dataset/kaldi_io.py
wenet/dataset/processor.py
wenet/dataset/rev_processor.py
wenet/dataset/rev_processor_ex.py
wenet/dataset/wav_distortion.py
wenet/dataset/deprecated/dataset.py
wenet/dataset/deprecated/processor.py
wenet/e_branchformer/encoder.py
wenet/e_branchformer/encoder_layer.py
wenet/efficient_conformer/__init__.py
wenet/efficient_conformer/attention.py
wenet/efficient_conformer/convolution.py
wenet/efficient_conformer/encoder.py
wenet/efficient_conformer/encoder_layer.py
wenet/efficient_conformer/subsampling.py
wenet/espnet/__init__.py
wenet/espnet/beam_search_timesync.py
wenet/finetune/lora/attention.py
wenet/finetune/lora/encoder.py
wenet/finetune/lora/layers.py
wenet/finetune/lora/utils.py
wenet/k2/__init__.py
wenet/k2/model.py
wenet/onmt_translate/beam_search.py
wenet/onmt_translate/penalties.py
wenet/paraformer/__init__.py
wenet/paraformer/attention.py
wenet/paraformer/cif.py
wenet/paraformer/convert_paraformer_to_wenet_config_and_ckpt.py
wenet/paraformer/embedding.py
wenet/paraformer/layers.py
wenet/paraformer/paraformer.py
rev_reverb-0.1.0.dist-info/LICENSE
rev_reverb-0.1.0.dist-info/METADATA
rev_reverb-0.1.0.dist-info/WHEEL
rev_reverb-0.1.0.dist-info/entry_points.txt
rev_reverb-0.1.0.dist-info/top_level.txt
rev_reverb-0.1.0.dist-info/RECORD
