Metadata-Version: 2.1
Name: rev-reverb
Version: 0.1.0
Summary: A simplified python packge to interact with the reverb models
Author-email: Rev Speechteam <speechteam@rev.com>
Maintainer-email: Rev Speechteam <speechteam@rev.com>
License: Apache License
Keywords: asr,reverb,rev,diarization
Classifier: Development Status :: 5 - Production/Stable
Classifier: Programming Language :: Python :: 3.10
Requires-Python: >=3.10
License-File: LICENSE
Requires-Dist: torchaudio==2.2.2
Requires-Dist: torch==2.2.2
Requires-Dist: openai-whisper
Requires-Dist: typeguard==2.*
Requires-Dist: wandb
Requires-Dist: pyyaml
Requires-Dist: numpy<2
Requires-Dist: GitPython
